dmapi/__init__.py
dmapi/dmapi.py
dmapi-0.0.1.dist-info/LICENSE
dmapi-0.0.1.dist-info/METADATA
dmapi-0.0.1.dist-info/WHEEL
dmapi-0.0.1.dist-info/top_level.txt
dmapi-0.0.1.dist-info/RECORD
