Metadata-Version: 2.1
Name: dmapi
Version: 0.0.1
Summary: A Python client for Dados de Mercado
Home-page: https://github.com/dadosdemercado/dmapi-python
Author: Dados de Mercado
Author-email: api@dadosdemercado.com
License: UNKNOWN
Platform: UNKNOWN
Classifier: Intended Audience :: Developers
Classifier: License :: OSI Approved :: MIT License
Classifier: Operating System :: OS Independent
Classifier: Programming Language :: Python :: 3.6
Classifier: Programming Language :: Python :: 3.7
Classifier: Programming Language :: Python :: 3.8
Requires-Python: >=3.6
